llmbda_fastapi/__init__.py
llmbda_fastapi/chains.py
llmbda_fastapi/env.py
llmbda_fastapi/transformations.py
llmbda_fastapi/frontend/__init__.py
llmbda_fastapi/frontend/input_components.py
llmbda_fastapi/frontend/upload_file.py
llmbda_fastapi-0.0.20.dist-info/METADATA
llmbda_fastapi-0.0.20.dist-info/WHEEL
llmbda_fastapi-0.0.20.dist-info/top_level.txt
llmbda_fastapi-0.0.20.dist-info/RECORD
