Metadata-Version: 2.1
Name: llmbda-fastapi
Version: 0.0.20
Home-page: https://relevanceai.com/
Author: Relevance AI
Author-email: jacky@relevanceai.com
Requires-Dist: fastapi
Requires-Dist: pydantic
Requires-Dist: requests
Requires-Dist: six
Requires-Dist: sniffio
Requires-Dist: starlette
Requires-Dist: tqdm
Requires-Dist: typing-extensions
Requires-Dist: tzdata
Requires-Dist: urllib3
Requires-Dist: uvicorn
Requires-Dist: wincertstore
Requires-Dist: relevanceai
